upguard/Account.py
upguard/BaseObject.py
upguard/Questionnaire.py
upguard/QuestionnaireAttachment.py
upguard/QuestionnaireAttachmentList.py
upguard/QuestionnaireList.py
upguard/TyposquatDomain.py
upguard/TyposquatDomainList.py
upguard/Vendor.py
upguard/VendorList.py
upguard/Version.py
upguard/Vulnerability.py
upguard/VulnerabilityList.py
upguard/__init__.py
upguard-0.0.23.dist-info/METADATA
upguard-0.0.23.dist-info/WHEEL
upguard-0.0.23.dist-info/top_level.txt
upguard-0.0.23.dist-info/RECORD
