Metadata-Version: 2.1
Name: upguard
Version: 0.0.23
Summary: UpGuard SDK for Python
Home-page: UNKNOWN
Author: UpGuard
Author-email: support@upguard.com
License: UNKNOWN
Platform: UNKNOWN
Classifier: Programming Language :: Python :: 2
Classifier: Programming Language :: Python :: 2.7
Classifier: Programming Language :: Python :: 3
Classifier: License :: Other/Proprietary License
Classifier: Operating System :: OS Independent
Requires-Dist: requests
